fusemap/__init__.py
fusemap/config.py
fusemap/dataset.py
fusemap/deconvolution.py
fusemap/logger.py
fusemap/loss.py
fusemap/model.py
fusemap/permutation.py
fusemap/preprocess.py
fusemap/spatial_integrate.py
fusemap/spatial_map.py
fusemap/train.py
fusemap/train_model.py
fusemap/utils.py
fusemap-0.0.2.dist-info/licenses/LICENSE
fusemap-0.0.2.dist-info/METADATA
fusemap-0.0.2.dist-info/WHEEL
fusemap-0.0.2.dist-info/entry_points.txt
fusemap-0.0.2.dist-info/top_level.txt
fusemap-0.0.2.dist-info/RECORD
