Metadata-Version: 2.4
Name: fusemap
Version: 0.0.2
License-File: LICENSE
Requires-Dist: scanpy==1.9.3
Requires-Dist: torch==2.0.1
Requires-Dist: dgl==1.1.1
Requires-Dist: sparse==0.14.0
Requires-Dist: leidenalg==0.10.1
Requires-Dist: dglgo==0.0.2
Requires-Dist: streamlit==1.45.1
Requires-Dist: openai==1.82.1
Requires-Dist: langchain_anthropic==0.3.14
Requires-Dist: langchain==0.3.25
Requires-Dist: langchain-community==0.3.24
Requires-Dist: langchain-openai==0.3.18
Requires-Dist: audio-recorder-streamlit==0.0.10
Requires-Dist: plotly==6.1.2
Requires-Dist: harmonypy==0.0.10
Requires-Dist: langgraph==0.4.7
Requires-Dist: langgraph-prebuilt==0.2.2
Requires-Dist: langgraph-sdk==0.1.70
Requires-Dist: langsmith==0.3.43
Requires-Dist: easydict==1.13
Requires-Dist: numpy==1.26.2
Dynamic: description
Dynamic: description-content-type
Dynamic: license-file
Dynamic: requires-dist
